mcpizza/__init__.py
mcpizza/http_server.py
mcpizza/server.py
iflow_mcp_grahammcbain_mcpizza-0.1.3.dist-info/METADATA
iflow_mcp_grahammcbain_mcpizza-0.1.3.dist-info/WHEEL
iflow_mcp_grahammcbain_mcpizza-0.1.3.dist-info/entry_points.txt
iflow_mcp_grahammcbain_mcpizza-0.1.3.dist-info/top_level.txt
iflow_mcp_grahammcbain_mcpizza-0.1.3.dist-info/RECORD
