Metadata-Version: 2.4
Name: iflow-mcp_grahammcbain_mcpizza
Version: 0.1.3
Summary: MCP server for ordering pizza through Domino's API
Author-email: MCP Pizza <mcpizza@example.com>
License: MIT
Requires-Python: >=3.9
Requires-Dist: pizzapi>=0.0.1
Requires-Dist: requests>=2.25.0
Requires-Dist: pydantic>=1.8.0
Requires-Dist: mcp>=0.1.0
